popupfaucet/__init__.py
popupfaucet/__main__.py
popupfaucet-0.1.0b7.dist-info/METADATA
popupfaucet-0.1.0b7.dist-info/WHEEL
popupfaucet-0.1.0b7.dist-info/entry_points.txt
popupfaucet-0.1.0b7.dist-info/RECORD
