Metadata-Version: 2.3
Name: popupfaucet
Version: 0.1.0b7
Summary: Ethereum testnet faucet CLI
Author-email: wolovim <3621728+wolovim@users.noreply.github.com>
Requires-Python: >=3.8
Requires-Dist: click>=8.1.7
Requires-Dist: eth-account>=0.13.1
Requires-Dist: eth-utils>=4.1.1
Requires-Dist: inquirerpy>=0.3.4
Requires-Dist: requests>=2.32.3
Requires-Dist: rich>=13.7.1
